ia_storage/__init__.py
ia_storage/fields.py
ia_storage/models.py
ia_storage/storage.py
django_internetarchive_storage-0.1.0.dist-info/LICENSE
django_internetarchive_storage-0.1.0.dist-info/METADATA
django_internetarchive_storage-0.1.0.dist-info/WHEEL
django_internetarchive_storage-0.1.0.dist-info/top_level.txt
django_internetarchive_storage-0.1.0.dist-info/RECORD
