Metadata-Version: 2.1
Name: django-internetarchive-storage
Version: 0.1.0
Summary: A custom Django storage system for Internet Archive collections
Home-page: https://palewi.re/docs/django-internetarchive-storage
Author: Ben Welsh
Author-email: b@palewi.re
License: MIT
Project-URL: Maintainer, https://github.com/palewire
Project-URL: Source, https://github.com/palewire/django-internetarchive-storage
Project-URL: Tracker, https://github.com/palewire/django-internetarchive-storage/issues
Project-URL: Docs, https://palewi.re/docs/django-internetarchive-storage
Classifier: Development Status :: 5 - Production/Stable
Classifier: Programming Language :: Python
Classifier: Programming Language :: Python :: 3.7
Classifier: Programming Language :: Python :: 3.8
Classifier: Programming Language :: Python :: 3.9
Classifier: Programming Language :: Python :: 3.10
Classifier: License :: OSI Approved :: MIT License
License-File: LICENSE
Requires-Dist: internetarchive
